<annotation>
	<folder>Final Dengue Mosquito Images Data for Research</folder>
	<filename>233.PNG</filename>
	<path>F:\Desktop\Dengue_mosquitio_research\Final Dengue Mosquito Images Data for Research\233.PNG</path>
	<source>
		<database>Unknown</database>
	</source>
	<size>
		<width>300</width>
		<height>449</height>
		<depth>3</depth>
	</size>
	<segmented>0</segmented>
	<object>
		<name>dengue_mosquito</name>
		<pose>Unspecified</pose>
		<truncated>0</truncated>
		<difficult>0</difficult>
		<bndbox>
			<xmin>33</xmin>
			<ymin>87</ymin>
			<xmax>262</xmax>
			<ymax>430</ymax>
		</bndbox>
	</object>
</annotation>
